NaroNet
