Metadata-Version: 2.1
Name: NaroNet
Version: 1.0.32
Summary: NaroNet: discovery of tumor microenvironment elements from multiplex images.
Home-page: https://github.com/djimenezsanchez/NaroNet
Author: Daniel Jiménez-Sánchez
Author-email: danijimnzs@gmail.com
License: BSD 3-Clause License
Project-URL: Bug Tracker, https://github.com/djimenezsanchez/NaroNet/issues
Platform: UNKNOWN
Classifier: Programming Language :: Python :: 3
Classifier: Operating System :: OS Independent
Classifier: License :: OSI Approved :: BSD License
Requires-Python: >=3.7
License-File: LICENSE.txt
